<?xml version="1.0" encoding="utf-8"?>
<WebResource xmlns:xsi="http://www.w3.org/2001/XMLSchema-instance">
  <WebResourceId>{a86dd039-dab9-ea11-a812-000d3a7fedbe}</WebResourceId>
  <Name>north52_/formula/leidos_anticipatedspendprofile/8IC/f.a86dd039dab9ea11a812000d3a7fedbe</Name>
  <DisplayName>4aff921e-c86c-4cb4-95e4-801e6d2ddfb5</DisplayName>
  <Description>North52Formula: Spend Profile  - Update Spend Profile Amount</Description>
  <WebResourceType>4</WebResourceType>
  <IntroducedVersion>1.0</IntroducedVersion>
  <IsEnabledForMobileClient>0</IsEnabledForMobileClient>
  <IsAvailableForMobileOffline>0</IsAvailableForMobileOffline>
  <IsCustomizable>1</IsCustomizable>
  <CanBeDeleted>1</CanBeDeleted>
  <IsHidden>0</IsHidden>
  <FileName>/WebResources/north52_formulaleidos_anticipatedspendprofile8ICfaA86DD039-DAB9-EA11-A812-000D3A7FEDBE</FileName>
</WebResource>