<?xml version="1.0" encoding="utf-8"?>
<WebResource xmlns:xsi="http://www.w3.org/2001/XMLSchema-instance">
  <WebResourceId>{7287ce66-0704-4577-a431-fbf775858a60}</WebResourceId>
  <Name>north52_/formula/leidos_programme/Wv2/fd.7287ce6607044577a431fbf775858a60</Name>
  <DisplayName>8c1503ef-ad23-4bde-b226-3d5e35662aa0</DisplayName>
  <Description>North52FormulaDetail: ListCostFundingProgramme</Description>
  <WebResourceType>4</WebResourceType>
  <IntroducedVersion>1.15.0.1708</IntroducedVersion>
  <IsEnabledForMobileClient>0</IsEnabledForMobileClient>
  <IsAvailableForMobileOffline>0</IsAvailableForMobileOffline>
  <IsCustomizable>1</IsCustomizable>
  <CanBeDeleted>1</CanBeDeleted>
  <IsHidden>0</IsHidden>
  <FileName>/WebResources/north52_formulaleidos_programmeWv2fd7287ce660704457287CE66-0704-4577-A431-FBF775858A60</FileName>
</WebResource>