<?xml version="1.0" encoding="utf-8"?>
<WebResource xmlns:xsi="http://www.w3.org/2001/XMLSchema-instance">
  <WebResourceId>{2570ac35-a1bd-eb11-bacc-000d3ad6a8e8}</WebResourceId>
  <Name>north52_/formula/leidos_ownhandinvoicesummary/tAx/f.2570ac35a1bdeb11bacc000d3ad6a8e8</Name>
  <DisplayName>474abf04-df12-409b-b4f0-7efee0cfc10f</DisplayName>
  <Description>North52Formula: Own Hand Invoice Summary - Save - Perform Action - Requested By and On</Description>
  <WebResourceType>4</WebResourceType>
  <IntroducedVersion>1.0</IntroducedVersion>
  <IsEnabledForMobileClient>0</IsEnabledForMobileClient>
  <IsAvailableForMobileOffline>0</IsAvailableForMobileOffline>
  <IsCustomizable>1</IsCustomizable>
  <CanBeDeleted>1</CanBeDeleted>
  <IsHidden>0</IsHidden>
  <FileName>/WebResources/north52_formulaleidos_ownhandinvoicesummarytAxf2572570AC35-A1BD-EB11-BACC-000D3AD6A8E8</FileName>
</WebResource>