<?xml version="1.0" encoding="utf-8"?>
<WebResource xmlns:xsi="http://www.w3.org/2001/XMLSchema-instance">
  <WebResourceId>{dd60c5ac-c9bf-4c8f-a959-6f845d8a8a90}</WebResourceId>
  <Name>north52_/formula/leidos_projectcost/KtA/fd.dd60c5acc9bf4c8fa9596f845d8a8a90</Name>
  <DisplayName>b687d73b-b5bf-4514-a5a1-92bb6467e7ef</DisplayName>
  <Description>North52FormulaDetail: List of Non Complete Programme Cost</Description>
  <WebResourceType>4</WebResourceType>
  <IntroducedVersion>1.0</IntroducedVersion>
  <IsEnabledForMobileClient>0</IsEnabledForMobileClient>
  <IsAvailableForMobileOffline>0</IsAvailableForMobileOffline>
  <IsCustomizable>1</IsCustomizable>
  <CanBeDeleted>1</CanBeDeleted>
  <IsHidden>0</IsHidden>
  <FileName>/WebResources/north52_formulaleidos_projectcostKtAfddd60c5acc9bfDD60C5AC-C9BF-4C8F-A959-6F845D8A8A90</FileName>
</WebResource>