<?xml version="1.0" encoding="utf-8"?>
<WebResource xmlns:xsi="http://www.w3.org/2001/XMLSchema-instance">
  <WebResourceId>{7bba3aad-8777-eb11-a812-002248414cc3}</WebResourceId>
  <Name>north52_/formula/connection/0hi/f.7bba3aad8777eb11a812002248414cc3</Name>
  <DisplayName>8f927e26-1cea-461f-9009-e8c8aab639d8</DisplayName>
  <Description>North52Formula: Connection - Save - Perform Action - Thu Feb 25 2021 16:37:01 GMT+0000 (Greenwich Mean Time)</Description>
  <WebResourceType>4</WebResourceType>
  <IntroducedVersion>1.0</IntroducedVersion>
  <IsEnabledForMobileClient>0</IsEnabledForMobileClient>
  <IsAvailableForMobileOffline>0</IsAvailableForMobileOffline>
  <IsCustomizable>1</IsCustomizable>
  <CanBeDeleted>1</CanBeDeleted>
  <IsHidden>0</IsHidden>
  <FileName>/WebResources/north52_formulaconnection0hif7bba3aad8777eb11a81207BBA3AAD-8777-EB11-A812-002248414CC3</FileName>
</WebResource>