<?xml version="1.0" encoding="utf-8"?>
<WebResource xmlns:xsi="http://www.w3.org/2001/XMLSchema-instance">
  <WebResourceId>{2de6ecc5-3ab5-ea11-a812-000d3a7fedbe}</WebResourceId>
  <Name>north52_/formula/leidos_supportitem/ymH/f.2de6ecc53ab5ea11a812000d3a7fedbe</Name>
  <DisplayName>773cfc9e-ea1e-4223-9dc2-d5be9b23d588</DisplayName>
  <Description>North52Formula: Support Item - Validation - Check Funding Allocation against Programme</Description>
  <WebResourceType>4</WebResourceType>
  <IntroducedVersion>1.0</IntroducedVersion>
  <IsEnabledForMobileClient>0</IsEnabledForMobileClient>
  <IsAvailableForMobileOffline>0</IsAvailableForMobileOffline>
  <IsCustomizable>1</IsCustomizable>
  <CanBeDeleted>1</CanBeDeleted>
  <IsHidden>0</IsHidden>
  <FileName>/WebResources/north52_formulaleidos_supportitemymHf2de6ecc53ab5e2DE6ECC5-3AB5-EA11-A812-000D3A7FEDBE</FileName>
</WebResource>