<?xml version="1.0" encoding="utf-8"?>
<WebResource xmlns:xsi="http://www.w3.org/2001/XMLSchema-instance">
  <WebResourceId>{e5ec66b7-6cfe-ea11-a813-000d3a7f1bbb}</WebResourceId>
  <Name>leidos_project.js</Name>
  <DisplayName>/leidos/project.js</DisplayName>
  <WebResourceType>3</WebResourceType>
  <IntroducedVersion>1.7.0.997</IntroducedVersion>
  <IsEnabledForMobileClient>0</IsEnabledForMobileClient>
  <IsAvailableForMobileOffline>0</IsAvailableForMobileOffline>
  <DependencyXml>&lt;Dependencies&gt;&lt;Dependency componentType="WebResource"/&gt;&lt;/Dependencies&gt;</DependencyXml>
  <IsCustomizable>1</IsCustomizable>
  <CanBeDeleted>1</CanBeDeleted>
  <IsHidden>0</IsHidden>
  <FileName>/WebResources/leidos_projectjsE5EC66B7-6CFE-EA11-A813-000D3A7F1BBB</FileName>
</WebResource>