<?xml version="1.0" encoding="utf-8"?>
<WebResource xmlns:xsi="http://www.w3.org/2001/XMLSchema-instance">
  <WebResourceId>{aaacf224-097a-486c-b24f-142047862254}</WebResourceId>
  <Name>north52_/formula/leidos_loanadjustment/4is/fd.aaacf224097a486cb24f142047862254</Name>
  <DisplayName>bcb6b999-889e-4be6-a1f0-7b91172792ac</DisplayName>
  <Description>North52FormulaDetail: Get Approved Adjustment Interest Amounts</Description>
  <WebResourceType>4</WebResourceType>
  <IntroducedVersion>1.14.0.1534</IntroducedVersion>
  <IsEnabledForMobileClient>0</IsEnabledForMobileClient>
  <IsAvailableForMobileOffline>0</IsAvailableForMobileOffline>
  <IsCustomizable>1</IsCustomizable>
  <CanBeDeleted>1</CanBeDeleted>
  <IsHidden>0</IsHidden>
  <FileName>/WebResources/north52_formulaleidos_loanadjustment4isfdaaacf2240AAACF224-097A-486C-B24F-142047862254</FileName>
</WebResource>