<?xml version="1.0" encoding="utf-8"?>
<WebResource xmlns:xsi="http://www.w3.org/2001/XMLSchema-instance">
  <WebResourceId>{e2eb2740-c630-eb11-a813-000d3a7fedbe}</WebResourceId>
  <Name>north52_/formula/leidos_paymentclaim/7Za/fd.e2eb2740c630eb11a813000d3a7fedbe</Name>
  <DisplayName>9ec1c7ff-0c29-42ea-bd65-6b6b0cbf1d43</DisplayName>
  <Description>North52FormulaDetail: PaidClaimsbyCategory</Description>
  <WebResourceType>4</WebResourceType>
  <IntroducedVersion>1.0.0.0</IntroducedVersion>
  <IsEnabledForMobileClient>0</IsEnabledForMobileClient>
  <IsAvailableForMobileOffline>0</IsAvailableForMobileOffline>
  <IsCustomizable>1</IsCustomizable>
  <CanBeDeleted>1</CanBeDeleted>
  <IsHidden>0</IsHidden>
  <FileName>/WebResources/north52_formulaleidos_paymentclaim7Zafde2eb2740c63E2EB2740-C630-EB11-A813-000D3A7FEDBE</FileName>
</WebResource>