<?xml version="1.0" encoding="utf-8"?>
<WebResource xmlns:xsi="http://www.w3.org/2001/XMLSchema-instance">
  <WebResourceId>{692beb3b-8c86-4f3d-a30b-dc561824ffdb}</WebResourceId>
  <Name>north52_/formula/leidos_loanadjustment/hhF/fd.692beb3b8c864f3da30bdc561824ffdb</Name>
  <DisplayName>7bbb982f-b86c-479d-8404-afc328d72103</DisplayName>
  <Description>North52FormulaDetail: FetchThirdPartySalaries</Description>
  <WebResourceType>4</WebResourceType>
  <IntroducedVersion>1.18.0.3609</IntroducedVersion>
  <IsEnabledForMobileClient>0</IsEnabledForMobileClient>
  <IsAvailableForMobileOffline>0</IsAvailableForMobileOffline>
  <IsCustomizable>1</IsCustomizable>
  <CanBeDeleted>1</CanBeDeleted>
  <IsHidden>0</IsHidden>
  <FileName>/WebResources/north52_formulaleidos_loanadjustmenthhFfd692beb3b8692BEB3B-8C86-4F3D-A30B-DC561824FFDB</FileName>
</WebResource>