<?xml version="1.0" encoding="utf-8"?>
<WebResource xmlns:xsi="http://www.w3.org/2001/XMLSchema-instance">
  <WebResourceId>{01bd981f-0d7a-ec11-8d21-002248433a59}</WebResourceId>
  <Name>north52_/formula/leidos_project/hr0/f.01bd981f0d7aec118d21002248433a59</Name>
  <DisplayName>137e21d1-7371-4744-bd7c-f73bba8e2c23</DisplayName>
  <Description>North52Formula: Project - Process Genie - Set Client Remaining Balance</Description>
  <WebResourceType>4</WebResourceType>
  <IntroducedVersion>1.0</IntroducedVersion>
  <IsEnabledForMobileClient>0</IsEnabledForMobileClient>
  <IsAvailableForMobileOffline>0</IsAvailableForMobileOffline>
  <IsCustomizable>1</IsCustomizable>
  <CanBeDeleted>1</CanBeDeleted>
  <IsHidden>0</IsHidden>
  <FileName>/WebResources/north52_formulaleidos_projecthr0f01bd981f0d7aec11801BD981F-0D7A-EC11-8D21-002248433A59</FileName>
</WebResource>