{"properties":{"connectionReferences":{"shared_commondataserviceforapps":{"runtimeSource":"embedded","connection":{},"api":{"name":"shared_commondataserviceforapps"}}},"definition":{"$schema":"https://schema.management.azure.com/providers/Microsoft.Logic/schemas/2016-06-01/workflowdefinition.json#","contentVersion":"1.0.0.0","parameters":{"$connections":{"defaultValue":{},"type":"Object"},"$authentication":{"defaultValue":{},"type":"SecureObject"}},"triggers":{"Recurrence":{"recurrence":{"frequency":"Week","interval":1},"type":"Recurrence"}},"actions":{"List_AMR_Due_in_next_8_weeks":{"runAfter":{},"type":"OpenApiConnection","inputs":{"host":{"connectionName":"shared_commondataserviceforapps","operationId":"ListRecords","apiId":"/providers/Microsoft.PowerApps/apis/shared_commondataserviceforapps"},"parameters":{"entityName":"leidos_accountmanagementrecords","fetchXml":"<fetch version=\"1.0\" output-format=\"xml-platform\" mapping=\"logical\" distinct=\"false\">\n  <entity name=\"leidos_accountmanagementrecord\">\n    <attribute name=\"leidos_name\" />\n    <attribute name=\"leidos_accountmanagementrecordid\" />\n    <order attribute=\"leidos_name\" descending=\"false\" />\n    <filter type=\"and\">\n      <condition attribute=\"statuscode\" operator=\"eq\" value=\"445260000\" />\n      <condition attribute=\"leidos_businessreviewreminderdate\" operator=\"next-x-weeks\" value=\"8\" />\n      <condition attribute=\"leidos_weekremindersent\" operator=\"ne\" value=\"1\" />\n    </filter>\n  </entity>\n</fetch>"},"authentication":"@parameters('$authentication')"}}},"outputs":{}}},"schemaVersion":"1.0.0.0"}