<?xml version="1.0" encoding="utf-8"?>
<WebResource xmlns:xsi="http://www.w3.org/2001/XMLSchema-instance">
  <WebResourceId>{a275541a-d15c-eb11-a812-00224840f2c5}</WebResourceId>
  <Name>north52_/formula/leidos_claim/MSd/fd.a275541ad15ceb11a81200224840f2c5</Name>
  <DisplayName>2fee12af-dfbb-4f0b-bcd4-9808dd557ac2</DisplayName>
  <Description>North52FormulaDetail: CostItemType</Description>
  <WebResourceType>4</WebResourceType>
  <IntroducedVersion>1.0</IntroducedVersion>
  <IsEnabledForMobileClient>0</IsEnabledForMobileClient>
  <IsAvailableForMobileOffline>0</IsAvailableForMobileOffline>
  <IsCustomizable>1</IsCustomizable>
  <CanBeDeleted>1</CanBeDeleted>
  <IsHidden>0</IsHidden>
  <FileName>/WebResources/north52_formulaleidos_claimMSdfda275541ad15ceb11a8A275541A-D15C-EB11-A812-00224840F2C5</FileName>
</WebResource>